<?xml version="1.0" encoding="UTF-8" ?>
<document>
	<loc>http://dantri.com.vn/giai-tri/10-my-nhan-trinh-dien-vay-da-hoi-dep-nhat-1315954668.htm</loc>
	<local>http://localhost:8080/local/10-my-nhan-trinh-dien-vay-da-hoi-dep-nhat-1315954668.htm</local>
	<title>10 mỹ nhân trình diễn váy dạ hội đẹp nhất | Giải trí | Dân trí</title>
	<published> 10/09/2011</published>
	<dateSum>15226</dateSum>
	<writer></writer>
	<body>    Philippines Malaysia Hi Lạp Pháp Puerto Rico Mexico Úc Ukraine Trung Quốc Paraguay Vĩnh Ngọc Theo GB</body>
	<category>Dân trí  ›   - Giải trí  ›   - </category>
	<description></description>
	<keywords></keywords>
	<engine></engine>
</document>