<?xml version="1.0" encoding="UTF-8" ?>
<document>
	<loc>http://dantri.com.vn/tinh-yeu-gioi-tinh/11-em-be-sinh-ra-da-giong-nguoi-noi-tieng-1426299561.htm</loc>
	<local>http://localhost:8080/local/11-em-be-sinh-ra-da-giong-nguoi-noi-tieng-1426299561.htm</local>
	<title>11 em bé sinh ra đã giống người nổi tiếng - Dân trí mobile</title>
	<published></published>
	<dateSum>0</dateSum>
	<writer></writer>
	<body></body>
	<category></category>
	<description>(Dân trí) - Những tấm hình so sánh các em bé và người nổi tiếng dưới đây sẽ khiến bạn ồ lên kinh ngạc "sao có thể giống đến vậy!" dù họ hoàn toàn không liên quan đến nhau.  - Dân trí mobile</description>
	<keywords></keywords>
	<engine></engine>
</document>